sdspconv_wrapper/__init__.py
sdspconv_wrapper/main.py
sdspconv_wrapper/sdspconv-dist/converter-backend.bat
sdspconv_wrapper/sdspconv-dist/converter-backend.sh
sdspconv_wrapper/sdspconv-dist/converter-fm2lm.bat
sdspconv_wrapper/sdspconv-dist/converter-fm2lm.sh
sdspconv_wrapper/sdspconv-dist/converter-frontend.bat
sdspconv_wrapper/sdspconv-dist/converter-frontend.sh
sdspconv_wrapper/sdspconv-dist/converter-main.bat
sdspconv_wrapper/sdspconv-dist/converter-main.sh
sdspconv_wrapper/sdspconv-dist/converter-packer.bat
sdspconv_wrapper/sdspconv-dist/converter-packer.sh
sdspconv_wrapper/sdspconv-dist/exec.properties
sdspconv_wrapper/sdspconv-dist/exec_win.properties
sdspconv_wrapper/sdspconv-dist/sa.manifest.yaml
sdspconv_wrapper/sdspconv-dist/sdspconv
sdspconv_wrapper/sdspconv-dist/sdspconv.bat
sdspconv_wrapper/sdspconv-dist/tiling-advisor.bat
sdspconv_wrapper/sdspconv-dist/tiling-advisor.sh
sdspconv_wrapper/sdspconv-dist/version.properties
sdspconv_wrapper/sdspconv-dist/converter-backend/jib-classpath-file
sdspconv_wrapper/sdspconv-dist/converter-backend/jib-main-class-file
sdspconv_wrapper/sdspconv-dist/converter-backend/classes/MainBE.class
sdspconv_wrapper/sdspconv-dist/converter-backend/classes/converter/CaracalSystemDefines.class
sdspconv_wrapper/sdspconv-dist/converter-backend/classes/converter/ConverterBE.class
sdspconv_wrapper/sdspconv-dist/converter-backend/classes/converter/SystemDefines.class
sdspconv_wrapper/sdspconv-dist/converter-backend/classes/converter/SystemExitCode.class
sdspconv_wrapper/sdspconv-dist/converter-backend/classes/converter/TigerSystemDefines.class
sdspconv_wrapper/sdspconv-dist/converter-backend/classes/converter/VersionHandler.class
sdspconv_wrapper/sdspconv-dist/converter-backend/classes/services/OptLevel.class
sdspconv_wrapper/sdspconv-dist/converter-backend/resources/LynxScpuBoot.bin
sdspconv_wrapper/sdspconv-dist/converter-backend/resources/LynxScpuExplorationCopy.bin
sdspconv-3.17.1.dist-info/METADATA
sdspconv-3.17.1.dist-info/WHEEL
sdspconv-3.17.1.dist-info/entry_points.txt
sdspconv-3.17.1.dist-info/top_level.txt
sdspconv-3.17.1.dist-info/RECORD
