Metadata-Version: 2.4
Name: sdspconv
Version: 3.17.1
Summary: sdspconv python wrapper
Author: ssi-dnn-dev
Author-email: ssi-dnn-dev@sony.com
Maintainer: ssi-dnn-dev
Maintainer-email: ssi-dnn-dev@sony.com
Requires-Dist: conv-allocator==3.17.1
Dynamic: author
Dynamic: author-email
Dynamic: maintainer
Dynamic: maintainer-email
Dynamic: requires-dist
Dynamic: summary
